LICENSE
MANIFEST.in
README.md
setup.py
libtestingtools/__init__.py
libtestingtools/api_github.py
libtestingtools.egg-info/PKG-INFO
libtestingtools.egg-info/SOURCES.txt
libtestingtools.egg-info/dependency_links.txt
libtestingtools.egg-info/not-zip-safe
libtestingtools.egg-info/requires.txt
libtestingtools.egg-info/top_level.txt