Metadata-Version: 2.1
Name: libtestingtools
Version: 0.2
Summary: Módulo para aprendisagem e construção de projetos Python
Home-page: https://github.com/lucasfmerino/dev_tools_tests
Author: Lucas Fonseca Merino
Author-email: lucasfmerino@gmail.com
License: GNU AFFERO GENERAL PUBLIC LICENSE
Classifier: Development Status :: 2 - Pre-Alpha
Classifier: Environment :: Console
Classifier: Intended Audience :: Developers
Classifier: License :: OSI Approved :: GNU Affero General Public License v3 or later (AGPLv3+)
Classifier: Operating System :: OS Independent
Classifier: Programming Language :: Python
Classifier: Programming Language :: Python :: 3.6
Classifier: Framework :: Pytest
License-File: LICENSE
